hubertchen_package/__init__.py
hubertchen_package/conn.py
hubertchen_package/my_jwt.py
hubertchen_package-0.6.dist-info/LICENSE
hubertchen_package-0.6.dist-info/METADATA
hubertchen_package-0.6.dist-info/WHEEL
hubertchen_package-0.6.dist-info/top_level.txt
hubertchen_package-0.6.dist-info/RECORD
