Metadata-Version: 2.1
Name: hubertchen_package
Version: 0.6
Summary: Hubert Chens Python package
Home-page: https://github.com/hubertchen200/mypy-package
Author: Hubert Chen
Author-email: hubertchen200@gmail.com
License: MIT
Classifier: Programming Language :: Python :: 3
Classifier: License :: OSI Approved :: MIT License
Classifier: Operating System :: OS Independent
Requires-Python: >=3.9
License-File: LICENSE
